falca/__init__.py
falca/actions.py
falca/app.py
falca/cli/__init__.py
falca/cli/__main__.py
falca/cli/app.py
falca/cli/base.py
falca/cli/inspect.py
falca/cli/runserver.py
falca/cli/shell.py
falca/compat.py
falca/depends/__init__.py
falca/depends/base.py
falca/depends/marshmallow.py
falca/depends/pydantic.py
falca/exceptions.py
falca/handlers.py
falca/helpers.py
falca/media/__init__.py
falca/media/json.py
falca/middleware/__init__.py
falca/middleware/base.py
falca/middleware/files.py
falca/middleware/forms.py
falca/middleware/json.py
falca/middleware/resource.py
falca/plugins/__init__.py
falca/plugins/base.py
falca/plugins/manager.py
falca/py.typed
falca/request.py
falca/resource.py
falca/responses.py
falca/router.py
falca/scaffold.py
falca/serializers/__init__.py
falca/serializers/marshmallow.py
falca/serializers/pydantic.py
falca/settings.py
falca/templates/redoc.html
falca/templates/swagger.html
falca/testing.py
falca-2.4.0.dist-info/entry_points.txt
falca-2.4.0.dist-info/LICENSE
falca-2.4.0.dist-info/WHEEL
falca-2.4.0.dist-info/METADATA
falca-2.4.0.dist-info/RECORD
