Metadata-Version: 2.1
Name: falca
Version: 2.4.0
Summary: Falca is an intuitive REST APIs framework based on the falcon framework.
Home-page: https://github.com/aprilahijriyan/falca
License: MIT
Keywords: wsgi,asgi,framework,rest api
Author: aprilahijriyan
Author-email: hijriyan23@gmail.com
Requires-Python: >=3.7,<4.0
Classifier: Development Status :: 4 - Beta
Classifier: Environment :: Web Environment
Classifier: Intended Audience :: Developers
Classifier: License :: OSI Approved :: MIT License
Classifier: Operating System :: OS Independent
Classifier: Programming Language :: Python
Classifier: Programming Language :: Python :: 3
Classifier: Programming Language :: Python :: 3.7
Classifier: Programming Language :: Python :: 3.8
Classifier: Programming Language :: Python :: 3.9
Classifier: Topic :: Software Development :: Libraries :: Application Frameworks
Requires-Dist: Mako (>=1.1.4,<2.0.0)
Requires-Dist: falcon (>=3.0.0,<4.0.0)
Requires-Dist: ipython (>=7.23.1,<8.0.0)
Requires-Dist: requests-toolbelt (>=0.9.1,<0.10.0)
Requires-Dist: rich (>=10.1.0,<11.0.0)
Requires-Dist: six (>=1.15.0,<2.0.0)
Requires-Dist: typer[all] (>=0.3.2,<0.4.0)
Requires-Dist: typing-inspect (>=0.6.0,<0.7.0)
Project-URL: Repository, https://github.com/aprilahijriyan/falca
